gitrestore/__init__.py
gitrestore-0.0.2.dist-info/entry_points.txt
gitrestore-0.0.2.dist-info/LICENSE
gitrestore-0.0.2.dist-info/WHEEL
gitrestore-0.0.2.dist-info/METADATA
gitrestore-0.0.2.dist-info/RECORD
